setup.cfg
setup.py
leocornus/__init__.py
leocornus.django.ploneproxy.egg-info/PKG-INFO
leocornus.django.ploneproxy.egg-info/SOURCES.txt
leocornus.django.ploneproxy.egg-info/dependency_links.txt
leocornus.django.ploneproxy.egg-info/entry_points.txt
leocornus.django.ploneproxy.egg-info/namespace_packages.txt
leocornus.django.ploneproxy.egg-info/not-zip-safe
leocornus.django.ploneproxy.egg-info/requires.txt
leocornus.django.ploneproxy.egg-info/top_level.txt
leocornus/django/__init__.py
leocornus/django/ploneproxy/HISTORY.txt
leocornus/django/ploneproxy/LICENSE.GPL
leocornus/django/ploneproxy/LICENSE.txt
leocornus/django/ploneproxy/README.txt
leocornus/django/ploneproxy/__init__.py
leocornus/django/ploneproxy/admin.py
leocornus/django/ploneproxy/manage.py
leocornus/django/ploneproxy/settings.py
leocornus/django/ploneproxy/urls.py
leocornus/django/ploneproxy/utils.py
leocornus/django/ploneproxy/version.txt
leocornus/django/ploneproxy/views.py
leocornus/django/ploneproxy/authen/__init__.py
leocornus/django/ploneproxy/authen/backends.py
leocornus/django/ploneproxy/authen/middleware.py
leocornus/django/ploneproxy/authen/models.py
leocornus/django/ploneproxy/authen/handlers/__init__.py
leocornus/django/ploneproxy/authen/handlers/modpython.py
leocornus/django/ploneproxy/locale/en/LC_MESSAGES/django.mo
leocornus/django/ploneproxy/locale/en/LC_MESSAGES/django.po
leocornus/django/ploneproxy/locale/fr/LC_MESSAGES/django.mo
leocornus/django/ploneproxy/locale/fr/LC_MESSAGES/django.po
leocornus/django/ploneproxy/middleware/__init__.py
leocornus/django/ploneproxy/samples/apache-mod_python.conf
leocornus/django/ploneproxy/samples/httplib2-mailpw.py
leocornus/django/ploneproxy/samples/httplib2-pwreset.py
leocornus/django/ploneproxy/samples/httplib2-test.py
leocornus/django/ploneproxy/templates/base.html
leocornus/django/ploneproxy/templates/login.html
leocornus/django/ploneproxy/templates/logout.html
leocornus/django/ploneproxy/templates/mail_password.html
leocornus/django/ploneproxy/templates/password_reset.html