Metadata-Version: 1.0
Name: leocornus.django.ploneproxy
Version: 0.1beta2
Summary: Django Application as a Proxy to Plone Sites
Home-page: http://plonexp.leocorn.com/xp/leocornus.django.ploneproxy
Author: Sean Chen
Author-email: sean.chen@leocorn.com
License: GPL
Keywords: Python Plone Zope Django Proxy
Platform: UNKNOWN
Classifier: Development Status :: 5 - Production/Stable
Classifier: Environment :: Web Environment
Classifier: Framework :: Plone
Classifier: Intended Audience :: Developers
Classifier: License :: OSI Approved :: GNU General Public License (GPL)
Classifier: Programming Language :: Python
Classifier: Programming Language :: Zope
Classifier: Topic :: Software Development :: Libraries :: Python Modules
Classifier: Topic :: Utilities
